elefanpy/__init__.py
elefanpy/__main__.py
elefanpy/calendro/__init__.py
elefanpy/dataprep/__init__.py
elefanpy/fsbase/__init__.py
elefanpy/gensysco/__init__.py
elefanpy/horology/__init__.py
elefanpy/hptuner/__init__.py
elefanpy/keras/__init__.py
elefanpy/matf/__init__.py
elefanpy/matplotlib/__init__.py
elefanpy/mtnetbri/__init__.py
elefanpy/numpy/__init__.py
elefanpy/onnxkit/__init__.py
elefanpy/opsys/__init__.py
elefanpy/pandas/__init__.py
elefanpy/pyplot/__init__.py
elefanpy/randna/__init__.py
elefanpy/regex/__init__.py
elefanpy/rtenv/__init__.py
elefanpy/shuten/__init__.py
elefanpy/sklearn/__init__.py
elefanpy/tawizard/__init__.py
elefanpy/tensorflow/__init__.py
elefanpy-1.2.6.dist-info/LICENSE.txt
elefanpy-1.2.6.dist-info/METADATA
elefanpy-1.2.6.dist-info/WHEEL
elefanpy-1.2.6.dist-info/top_level.txt
elefanpy-1.2.6.dist-info/RECORD
